wneq/__about__.py
wneq/__init__.py
wneq/base.py
wneq/equil.py
wneq/ng.py
wneq-1.2.0.dist-info/licenses/LICENSE.txt
wneq-1.2.0.dist-info/METADATA
wneq-1.2.0.dist-info/WHEEL
wneq-1.2.0.dist-info/top_level.txt
wneq-1.2.0.dist-info/RECORD
