Metadata-Version: 2.4
Name: wneq
Version: 1.2.0
Summary: Package for nuclear equilibria
Author-email: "Bradley S. Meyer" <mbradle@g.clemson.edu>, Mengke Li <mengkel@g.clemson.edu>
Maintainer-email: "Bradley S. Meyer" <mbradle@g.clemson.edu>
License-Expression: GPL-3.0-or-later
Project-URL: Documentation, https://wneq.readthedocs.org
Project-URL: Repository, https://github.com/mbradle/wneq.git
Project-URL: Bug Tracker, https://github.com/mbradle/wneq/issues
Keywords: astronomy, nuclear astrophysics
Classifier: Development Status :: 5 - Production/Stable
Classifier: Intended Audience :: Science/Research
Classifier: Topic :: Scientific/Engineering :: Astronomy
Classifier: Programming Language :: Python :: 3
Requires-Python: >=3.0
License-File: LICENSE.txt
Requires-Dist: wnnet
Requires-Dist: numpy
Dynamic: license-file
